cvfinal/__init__.py
cvfinal/aaa.py
cvfinal/cvfinal.py
cvfinal-0.0.3.dist-info/METADATA
cvfinal-0.0.3.dist-info/WHEEL
cvfinal-0.0.3.dist-info/licenses/LICENSE.txt
cvfinal-0.0.3.dist-info/RECORD
